cloudmitigator_semantic/__init__.py
cloudmitigator_semantic/cli.py
cloudmitigator_semantic/git.py
cloudmitigator_semantic/utilities.py
cloudmitigator_semantic/version.py
cloudmitigator_semantic-0.1.6.dist-info/LICENSE
cloudmitigator_semantic-0.1.6.dist-info/METADATA
cloudmitigator_semantic-0.1.6.dist-info/WHEEL
cloudmitigator_semantic-0.1.6.dist-info/entry_points.txt
cloudmitigator_semantic-0.1.6.dist-info/top_level.txt
cloudmitigator_semantic-0.1.6.dist-info/RECORD
