Metadata-Version: 2.1
Name: cloudmitigator-semantic
Version: 0.1.6
Summary: Means of automating the release version of a git repo using git tags
Home-page: UNKNOWN
Author: Michael Schappacher
Author-email: m.a.schappacher@gmail.com
License: UNKNOWN
Platform: UNKNOWN
Requires-Dist: pyaml (==20.4.0)
Requires-Dist: PyYAML (==5.3.1)
Requires-Dist: Click (==7.0)
